jzsk_runid/__init__.py
jzsk_runid/mlflow_tools.py
jzsk_runid-0.0.5.dist-info/LICENSE
jzsk_runid-0.0.5.dist-info/METADATA
jzsk_runid-0.0.5.dist-info/WHEEL
jzsk_runid-0.0.5.dist-info/top_level.txt
jzsk_runid-0.0.5.dist-info/RECORD
